simplesecurity/__init__.py
simplesecurity/__main__.py
simplesecurity/excluded.py
simplesecurity/filter.py
simplesecurity/formatter.py
simplesecurity/level.py
simplesecurity/plugins.py
simplesecurity/semgrep_sec.yaml
simplesecurity/types.py
simplesecurity-2023.0.2.dist-info/entry_points.txt
simplesecurity-2023.0.2.dist-info/LICENSE.md
simplesecurity-2023.0.2.dist-info/METADATA
simplesecurity-2023.0.2.dist-info/WHEEL
simplesecurity-2023.0.2.dist-info/RECORD
