Metadata-Version: 2.1
Name: simplesecurity
Version: 2023.0.2
Summary: Combine multiple popular python security tools and generate reports or output into different formats
Home-page: https://github.com/FHPythonUtils/SimpleSecurity
License: MIT
Author: FredHappyface
Requires-Python: >=3.7,<4.0
Classifier: Development Status :: 5 - Production/Stable
Classifier: Environment :: Console
Classifier: Environment :: MacOS X
Classifier: Environment :: Win32 (MS Windows)
Classifier: Intended Audience :: Developers
Classifier: Intended Audience :: Education
Classifier: License :: OSI Approved :: MIT License
Classifier: Natural Language :: English
Classifier: Operating System :: OS Independent
Classifier: Programming Language :: Python :: 3
Classifier: Programming Language :: Python :: 3.7
Classifier: Programming Language :: Python :: 3.8
Classifier: Programming Language :: Python :: 3.9
Classifier: Programming Language :: Python :: 3.10
Classifier: Programming Language :: Python :: 3.11
Classifier: Programming Language :: Python :: Implementation :: CPython
Classifier: Topic :: Security
Classifier: Topic :: Software Development :: Libraries :: Python Modules
Classifier: Topic :: Utilities
Provides-Extra: full
Requires-Dist: bandit (>=1.7.5,<2) ; extra == "full"
Requires-Dist: dlint (>=0.14.1,<2) ; extra == "full"
Requires-Dist: dodgy (>=0.2.1,<2) ; extra == "full"
Requires-Dist: poetry (>=1.5.1,<2) ; extra == "full"
Requires-Dist: safety (>=2.3.5,<3) ; extra == "full"
Requires-Dist: semgrep (>=1.29.0,<2) ; extra == "full"
Project-URL: Documentation, https://github.com/FHPythonUtils/SimpleSecurity/blob/master/README.md
Project-URL: Repository, https://github.com/FHPythonUtils/SimpleSecurity
